scarab/__init__.py
scarab/bugzilla.py
scarab/cli.py
scarab/context.py
scarab/settings.py
scarab/ui.py
scarab/commands/__init__.py
scarab/commands/aflags.py
scarab/commands/attach.py
scarab/commands/base.py
scarab/commands/fetch.py
scarab/commands/fetchall.py
scarab/commands/files.py
scarab/commands/flags.py
scarab/commands/info.py
scarab/commands/products.py
scarab/commands/submit.py
scarab/commands/update.py
scarab-0.1.3.dist-info/LICENSE
scarab-0.1.3.dist-info/METADATA
scarab-0.1.3.dist-info/WHEEL
scarab-0.1.3.dist-info/entry_points.txt
scarab-0.1.3.dist-info/top_level.txt
scarab-0.1.3.dist-info/RECORD
