Metadata-Version: 2.1
Name: scarab
Version: 0.1.3
Summary: A FreBSD Bugzilla CLI client.
Home-page: https://github.com/gonzoua/scarab
Author: Oleksandr Tymoshenko
Author-email: gonzo@bluezbox.com
License: BSD 3-clause "New" or "Revised License"
Keywords: bugzilla cli freebsd
Platform: UNKNOWN
Classifier: Development Status :: 3 - Alpha
Classifier: Intended Audience :: Developers
Classifier: Topic :: Utilities
Classifier: License :: OSI Approved :: BSD License
Classifier: Natural Language :: English
Classifier: Operating System :: OS Independent
Classifier: Programming Language :: Python :: 3
Requires-Dist: python-magic
Provides-Extra: test
Requires-Dist: coverage ; extra == 'test'
Requires-Dist: pytest ; extra == 'test'
Requires-Dist: pytest-cov ; extra == 'test'
